<?xml version="1.0" encoding="UTF-8"?>
<equipamentos>
    <equipamento>
        <setor>Produção</setor>
        <tamanho>25</tamanho>
        <quantidade>10</quantidade>
        <defeituoso>false</defeituoso>
    </equipamento>
    <equipamento>
        <setor>Manutenção</setor>
        <tamanho>30</tamanho>
        <quantidade>5</quantidade>
        <defeituoso>true</defeituoso>
    </equipamento>
    <equipamento>
        <setor>Logística</setor>
        <tamanho>15</tamanho>
        <quantidade>20</quantidade>
        <defeituoso>false</defeituoso>
    </equipamento>
    <equipamento>
        <setor>Qualidade</setor>
        <tamanho>40</tamanho>
        <quantidade>8</quantidade>
        <defeituoso>false</defeituoso>
    </equipamento>
    <equipamento>
        <setor>Segurança</setor>
        <tamanho>50</tamanho>
        <quantidade>12</quantidade>
        <defeituoso>true</defeituoso>
    </equipamento>
    <equipamento>
        <setor>Administração</setor>
        <tamanho>35</tamanho>
        <quantidade>6</quantidade>
        <defeituoso>false</defeituoso>
    </equipamento>
    <equipamento>
        <setor>TI</setor>
        <tamanho>45</tamanho>
        <quantidade>15</quantidade>
        <defeituoso>false</defeituoso>
    </equipamento>
    <equipamento>
        <setor>Expedição</setor>
        <tamanho>20</tamanho>
        <quantidade>18</quantidade>
        <defeituoso>true</defeituoso>
    </equipamento>
</equipamentos>
